{"dados": {"id": 1163, "uri": "https://dadosabertos.camara.leg.br/api/v2/deputados/1163", "nomeCivil": "Olympio Oscar de Vilhena Valadão", "ultimoStatus": {"id": 1163, "uri": "https://dadosabertos.camara.leg.br/api/v2/deputados/1163", "nome": "OLÍMPIO VALADÃO", "siglaPartido": null, "uriPartido": null, "siglaUf": "MG", "idLegislatura": 20, "urlFoto": "https://www.camara.leg.br/internet/deputado/bandep/1163.jpg", "email": null, "data": null, "nomeEleitoral": "OLÍMPIO VALADÃO", "gabinete": {"nome": null, "predio": null, "sala": null, "andar": null, "telefone": null, "email": null}, "situacao": null, "condicaoEleitoral": "Titular", "descricaoStatus": null}, "cpf": null, "sexo": "M", "urlWebsite": null, "redeSocial": [], "dataNascimento": null, "dataFalecimento": null, "ufNascimento": null, "municipioNascimento": null, "escolaridade": null}, "links": [{"rel": "self", "href": "https://dadosabertos.camara.leg.br/api/v2/deputados/1163"}]}