{"dados": {"id": 116379, "uri": "https://dadosabertos.camara.leg.br/api/v2/deputados/116379", "nomeCivil": "DARCI DE MATOS", "ultimoStatus": {"id": 116379, "uri": "https://dadosabertos.camara.leg.br/api/v2/deputados/116379", "nome": "Darci de Matos", "siglaPartido": "PSD", "uriPartido": null, "siglaUf": "SC", "idLegislatura": 57, "urlFoto": "https://www.camara.leg.br/internet/deputado/bandep/116379.jpg", "email": null, "data": "2024-11-02", "nomeEleitoral": "Darci de Matos", "gabinete": {"nome": null, "predio": null, "sala": null, "andar": null, "telefone": null, "email": null}, "situacao": "Suplência", "condicaoEleitoral": "Suplente", "descricaoStatus": null}, "cpf": "44828624953", "sexo": "M", "urlWebsite": null, "redeSocial": [], "dataNascimento": "1961-11-08", "dataFalecimento": null, "ufNascimento": "PR", "municipioNascimento": "Cafelândia", "escolaridade": "Superior"}, "links": [{"rel": "self", "href": "https://dadosabertos.camara.leg.br/api/v2/deputados/116379"}]}