{"dados": {"id": 130260, "uri": "https://dadosabertos.camara.leg.br/api/v2/deputados/130260", "nomeCivil": "Homero Pires", "ultimoStatus": {"id": 130260, "uri": "https://dadosabertos.camara.leg.br/api/v2/deputados/130260", "nome": "HOMERO PIRES", "siglaPartido": "PSD", "uriPartido": null, "siglaUf": "BA", "idLegislatura": 37, "urlFoto": "https://www.camara.leg.br/internet/deputado/bandep/130260.jpg", "email": null, "data": null, "nomeEleitoral": "HOMERO PIRES", "gabinete": {"nome": null, "predio": null, "sala": null, "andar": null, "telefone": null, "email": null}, "situacao": "Vacância", "condicaoEleitoral": "Suplente", "descricaoStatus": null}, "cpf": null, "sexo": "M", "urlWebsite": null, "redeSocial": [], "dataNascimento": "1887-02-07", "dataFalecimento": null, "ufNascimento": "BA", "municipioNascimento": "Ituaçu", "escolaridade": "Superior"}, "links": [{"rel": "self", "href": "https://dadosabertos.camara.leg.br/api/v2/deputados/130260"}]}