{"dados": {"id": 130621, "uri": "https://dadosabertos.camara.leg.br/api/v2/deputados/130621", "nomeCivil": "José Quintela Cavalcanti", "ultimoStatus": {"id": 130621, "uri": "https://dadosabertos.camara.leg.br/api/v2/deputados/130621", "nome": "QUINTELA CAVALCANTI", "siglaPartido": "UDN", "uriPartido": null, "siglaUf": "AL", "idLegislatura": 40, "urlFoto": "https://www.camara.leg.br/internet/deputado/bandep/130621.jpg", "email": null, "data": null, "nomeEleitoral": "QUINTELA CAVALCANTI", "gabinete": {"nome": null, "predio": null, "sala": null, "andar": null, "telefone": null, "email": null}, "situacao": null, "condicaoEleitoral": "Suplente", "descricaoStatus": null}, "cpf": null, "sexo": "M", "urlWebsite": null, "redeSocial": [], "dataNascimento": "1894-07-16", "dataFalecimento": null, "ufNascimento": "AL", "municipioNascimento": "Pilar", "escolaridade": "Superior"}, "links": [{"rel": "self", "href": "https://dadosabertos.camara.leg.br/api/v2/deputados/130621"}]}