{"dados": {"id": 130846, "uri": "https://dadosabertos.camara.leg.br/api/v2/deputados/130846", "nomeCivil": "Nestor Pereira", "ultimoStatus": {"id": 130846, "uri": "https://dadosabertos.camara.leg.br/api/v2/deputados/130846", "nome": "NESTOR PEREIRA", "siglaPartido": "PRP", "uriPartido": null, "siglaUf": "RS", "idLegislatura": 41, "urlFoto": "https://www.camara.leg.br/internet/deputado/bandep/130846.jpg", "email": null, "data": null, "nomeEleitoral": "NESTOR PEREIRA", "gabinete": {"nome": null, "predio": null, "sala": null, "andar": null, "telefone": null, "email": null}, "situacao": null, "condicaoEleitoral": "Suplente", "descricaoStatus": null}, "cpf": null, "sexo": "M", "urlWebsite": null, "redeSocial": [], "dataNascimento": "1906-05-24", "dataFalecimento": null, "ufNascimento": "RS", "municipioNascimento": "Taquara", "escolaridade": "Superior"}, "links": [{"rel": "self", "href": "https://dadosabertos.camara.leg.br/api/v2/deputados/130846"}]}