{"dados": {"id": 131064, "uri": "https://dadosabertos.camara.leg.br/api/v2/deputados/131064", "nomeCivil": "Marcial Gonçalves Terra", "ultimoStatus": {"id": 131064, "uri": "https://dadosabertos.camara.leg.br/api/v2/deputados/131064", "nome": "MARCIAL TERRA", "siglaPartido": "PSD", "uriPartido": null, "siglaUf": "RS", "idLegislatura": 42, "urlFoto": "https://www.camara.leg.br/internet/deputado/bandep/131064.jpg", "email": null, "data": null, "nomeEleitoral": "MARCIAL TERRA", "gabinete": {"nome": null, "predio": null, "sala": null, "andar": null, "telefone": null, "email": null}, "situacao": "Vacância", "condicaoEleitoral": "Suplente", "descricaoStatus": null}, "cpf": null, "sexo": "M", "urlWebsite": null, "redeSocial": [], "dataNascimento": "1889-07-30", "dataFalecimento": null, "ufNascimento": "RS", "municipioNascimento": "Santo Ângelo", "escolaridade": null}, "links": [{"rel": "self", "href": "https://dadosabertos.camara.leg.br/api/v2/deputados/131064"}]}