{"dados": {"id": 131164, "uri": "https://dadosabertos.camara.leg.br/api/v2/deputados/131164", "nomeCivil": "Alvaro Coutinho da Mota", "ultimoStatus": {"id": 131164, "uri": "https://dadosabertos.camara.leg.br/api/v2/deputados/131164", "nome": "ALVARO MOTA", "siglaPartido": "ARENA", "uriPartido": null, "siglaUf": "RN", "idLegislatura": 43, "urlFoto": "https://www.camara.leg.br/internet/deputado/bandep/131164.jpg", "email": null, "data": null, "nomeEleitoral": "ALVARO MOTA", "gabinete": {"nome": null, "predio": null, "sala": null, "andar": null, "telefone": null, "email": null}, "situacao": null, "condicaoEleitoral": "Titular", "descricaoStatus": null}, "cpf": null, "sexo": "M", "urlWebsite": null, "redeSocial": [], "dataNascimento": "1934-09-22", "dataFalecimento": null, "ufNascimento": "PB", "municipioNascimento": "Campina Grande", "escolaridade": "Superior"}, "links": [{"rel": "self", "href": "https://dadosabertos.camara.leg.br/api/v2/deputados/131164"}]}