{"dados": {"id": 131253, "uri": "https://dadosabertos.camara.leg.br/api/v2/deputados/131253", "nomeCivil": "Henrique Henkin", "ultimoStatus": {"id": 131253, "uri": "https://dadosabertos.camara.leg.br/api/v2/deputados/131253", "nome": "HENRIQUE HENKIN", "siglaPartido": "MDB*", "uriPartido": null, "siglaUf": "RS", "idLegislatura": 43, "urlFoto": "https://www.camara.leg.br/internet/deputado/bandep/131253.jpg", "email": null, "data": null, "nomeEleitoral": "HENRIQUE HENKIN", "gabinete": {"nome": null, "predio": null, "sala": null, "andar": null, "telefone": null, "email": null}, "situacao": "Vacância", "condicaoEleitoral": "Suplente", "descricaoStatus": null}, "cpf": null, "sexo": "M", "urlWebsite": null, "redeSocial": [], "dataNascimento": "1917-01-13", "dataFalecimento": null, "ufNascimento": "RS", "municipioNascimento": "Erechim", "escolaridade": "Superior"}, "links": [{"rel": "self", "href": "https://dadosabertos.camara.leg.br/api/v2/deputados/131253"}]}