{"dados": {"id": 131260, "uri": "https://dadosabertos.camara.leg.br/api/v2/deputados/131260", "nomeCivil": "Jamil Amiden", "ultimoStatus": {"id": 131260, "uri": "https://dadosabertos.camara.leg.br/api/v2/deputados/131260", "nome": "JAMIL AMIDEN", "siglaPartido": "MDB*", "uriPartido": null, "siglaUf": "GB", "idLegislatura": 43, "urlFoto": "https://www.camara.leg.br/internet/deputado/bandep/131260.jpg", "email": null, "data": null, "nomeEleitoral": "JAMIL AMIDEN", "gabinete": {"nome": null, "predio": null, "sala": null, "andar": null, "telefone": null, "email": null}, "situacao": "Vacância", "condicaoEleitoral": "Titular", "descricaoStatus": null}, "cpf": null, "sexo": "M", "urlWebsite": null, "redeSocial": [], "dataNascimento": "1922-03-31", "dataFalecimento": null, "ufNascimento": "MS", "municipioNascimento": "Corumbá", "escolaridade": null}, "links": [{"rel": "self", "href": "https://dadosabertos.camara.leg.br/api/v2/deputados/131260"}]}