{"dados": {"id": 131475, "uri": "https://dadosabertos.camara.leg.br/api/v2/deputados/131475", "nomeCivil": "Paulo Alberto de Oliveira", "ultimoStatus": {"id": 131475, "uri": "https://dadosabertos.camara.leg.br/api/v2/deputados/131475", "nome": "PAULO ALBERTO", "siglaPartido": "ARENA", "uriPartido": null, "siglaUf": "SP", "idLegislatura": 44, "urlFoto": "https://www.camara.leg.br/internet/deputado/bandep/131475.jpg", "email": null, "data": null, "nomeEleitoral": "PAULO ALBERTO", "gabinete": {"nome": null, "predio": null, "sala": null, "andar": null, "telefone": null, "email": null}, "situacao": null, "condicaoEleitoral": "Titular", "descricaoStatus": null}, "cpf": "00139835048", "sexo": "M", "urlWebsite": null, "redeSocial": [], "dataNascimento": "1925-10-28", "dataFalecimento": null, "ufNascimento": "MG", "municipioNascimento": "Prata", "escolaridade": null}, "links": [{"rel": "self", "href": "https://dadosabertos.camara.leg.br/api/v2/deputados/131475"}]}