{"dados": {"id": 131590, "uri": "https://dadosabertos.camara.leg.br/api/v2/deputados/131590", "nomeCivil": "Marcos Wellington de Castro Tito", "ultimoStatus": {"id": 131590, "uri": "https://dadosabertos.camara.leg.br/api/v2/deputados/131590", "nome": "MARCOS TITO", "siglaPartido": "MDB*", "uriPartido": null, "siglaUf": "MG", "idLegislatura": 45, "urlFoto": "https://www.camara.leg.br/internet/deputado/bandep/131590.jpg", "email": null, "data": null, "nomeEleitoral": "MARCOS TITO", "gabinete": {"nome": null, "predio": null, "sala": null, "andar": null, "telefone": null, "email": null}, "situacao": null, "condicaoEleitoral": "Titular", "descricaoStatus": null}, "cpf": "00070138336", "sexo": "M", "urlWebsite": null, "redeSocial": [], "dataNascimento": "1940-09-22", "dataFalecimento": null, "ufNascimento": "MG", "municipioNascimento": "Belo Horizonte", "escolaridade": "Superior"}, "links": [{"rel": "self", "href": "https://dadosabertos.camara.leg.br/api/v2/deputados/131590"}]}