{"dados": {"id": 131737, "uri": "https://dadosabertos.camara.leg.br/api/v2/deputados/131737", "nomeCivil": "JORGE PAULO NOGUEIRA", "ultimoStatus": {"id": 131737, "uri": "https://dadosabertos.camara.leg.br/api/v2/deputados/131737", "nome": "JORGE PAULO", "siglaPartido": "PDS", "uriPartido": null, "siglaUf": "SP", "idLegislatura": 46, "urlFoto": "https://www.camara.leg.br/internet/deputado/bandep/131737.jpg", "email": null, "data": null, "nomeEleitoral": "JORGE PAULO", "gabinete": {"nome": null, "predio": null, "sala": null, "andar": null, "telefone": null, "email": null}, "situacao": null, "condicaoEleitoral": "Titular", "descricaoStatus": null}, "cpf": "04590562804", "sexo": "M", "urlWebsite": null, "redeSocial": [], "dataNascimento": "1938-04-23", "dataFalecimento": null, "ufNascimento": "SP", "municipioNascimento": "São Paulo", "escolaridade": null}, "links": [{"rel": "self", "href": "https://dadosabertos.camara.leg.br/api/v2/deputados/131737"}]}