{"dados": {"id": 131783, "uri": "https://dadosabertos.camara.leg.br/api/v2/deputados/131783", "nomeCivil": "Paulo Ferreira Studart", "ultimoStatus": {"id": 131783, "uri": "https://dadosabertos.camara.leg.br/api/v2/deputados/131783", "nome": "PAULO STUDART", "siglaPartido": "ARENA", "uriPartido": null, "siglaUf": "CE", "idLegislatura": 46, "urlFoto": "https://www.camara.leg.br/internet/deputado/bandep/131783.jpg", "email": null, "data": null, "nomeEleitoral": "PAULO STUDART", "gabinete": {"nome": null, "predio": null, "sala": null, "andar": null, "telefone": null, "email": null}, "situacao": "Vacância", "condicaoEleitoral": "Titular", "descricaoStatus": null}, "cpf": "00245976353", "sexo": "M", "urlWebsite": null, "redeSocial": [], "dataNascimento": "1925-07-18", "dataFalecimento": null, "ufNascimento": "CE", "municipioNascimento": "Fortaleza", "escolaridade": "Superior"}, "links": [{"rel": "self", "href": "https://dadosabertos.camara.leg.br/api/v2/deputados/131783"}]}