{"dados": {"id": 131717, "uri": "https://dadosabertos.camara.leg.br/api/v2/deputados/131717", "nomeCivil": "Januário Alves Feitosa", "ultimoStatus": {"id": 131717, "uri": "https://dadosabertos.camara.leg.br/api/v2/deputados/131717", "nome": "JANUÁRIO FEITOSA", "siglaPartido": "PDS", "uriPartido": null, "siglaUf": "CE", "idLegislatura": 46, "urlFoto": "https://www.camara.leg.br/internet/deputado/bandep/131717.jpg", "email": null, "data": null, "nomeEleitoral": "JANUÁRIO FEITOSA", "gabinete": {"nome": null, "predio": null, "sala": null, "andar": null, "telefone": null, "email": null}, "situacao": "Vacância", "condicaoEleitoral": "Suplente", "descricaoStatus": null}, "cpf": "00041572300", "sexo": "M", "urlWebsite": null, "redeSocial": [], "dataNascimento": "1914-12-28", "dataFalecimento": null, "ufNascimento": "PB", "municipioNascimento": "Cajazeiras", "escolaridade": null}, "links": [{"rel": "self", "href": "https://dadosabertos.camara.leg.br/api/v2/deputados/131717"}]}