{"dados": {"id": 131730, "uri": "https://dadosabertos.camara.leg.br/api/v2/deputados/131730", "nomeCivil": "Joaquim de Figueiredo Correia", "ultimoStatus": {"id": 131730, "uri": "https://dadosabertos.camara.leg.br/api/v2/deputados/131730", "nome": "FIGUEIREDO CORREIA", "siglaPartido": "PMDB", "uriPartido": null, "siglaUf": "CE", "idLegislatura": 46, "urlFoto": "https://www.camara.leg.br/internet/deputado/bandep/131730.jpg", "email": null, "data": null, "nomeEleitoral": "FIGUEIREDO CORREIA", "gabinete": {"nome": null, "predio": null, "sala": null, "andar": null, "telefone": null, "email": null}, "situacao": "Vacância", "condicaoEleitoral": "Titular", "descricaoStatus": null}, "cpf": "00033499349", "sexo": "M", "urlWebsite": null, "redeSocial": [], "dataNascimento": "1920-11-04", "dataFalecimento": null, "ufNascimento": "CE", "municipioNascimento": "Várzea Alegre", "escolaridade": "Superior"}, "links": [{"rel": "self", "href": "https://dadosabertos.camara.leg.br/api/v2/deputados/131730"}]}