{"dados": {"id": 131806, "uri": "https://dadosabertos.camara.leg.br/api/v2/deputados/131806", "nomeCivil": "Stoessel de Oliveira Dourado", "ultimoStatus": {"id": 131806, "uri": "https://dadosabertos.camara.leg.br/api/v2/deputados/131806", "nome": "STOESSEL DOURADO", "siglaPartido": "PDS", "uriPartido": null, "siglaUf": "BA", "idLegislatura": 46, "urlFoto": "https://www.camara.leg.br/internet/deputado/bandep/131806.jpg", "email": null, "data": null, "nomeEleitoral": "STOESSEL DOURADO", "gabinete": {"nome": null, "predio": null, "sala": null, "andar": null, "telefone": null, "email": null}, "situacao": null, "condicaoEleitoral": "Titular", "descricaoStatus": null}, "cpf": "04793900534", "sexo": "M", "urlWebsite": null, "redeSocial": [], "dataNascimento": "1931-09-28", "dataFalecimento": null, "ufNascimento": "BA", "municipioNascimento": "Paripiranga", "escolaridade": "Superior"}, "links": [{"rel": "self", "href": "https://dadosabertos.camara.leg.br/api/v2/deputados/131806"}]}