{"dados": {"id": 141392, "uri": "https://dadosabertos.camara.leg.br/api/v2/deputados/141392", "nomeCivil": "ARNALDO FRANÇA VIANNA", "ultimoStatus": {"id": 141392, "uri": "https://dadosabertos.camara.leg.br/api/v2/deputados/141392", "nome": "ARNALDO VIANNA", "siglaPartido": "PDT", "uriPartido": null, "siglaUf": "RJ", "idLegislatura": 53, "urlFoto": "https://www.camara.leg.br/internet/deputado/bandep/141392.jpg", "email": null, "data": "2011-01-31", "nomeEleitoral": "ARNALDO VIANNA", "gabinete": {"nome": null, "predio": null, "sala": null, "andar": null, "telefone": null, "email": null}, "situacao": "Fim de Mandato", "condicaoEleitoral": "Titular", "descricaoStatus": null}, "cpf": "26877619749", "sexo": "M", "urlWebsite": null, "redeSocial": [], "dataNascimento": "1947-11-04", "dataFalecimento": null, "ufNascimento": "RJ", "municipioNascimento": "Campos dos Goytacazes", "escolaridade": "Superior"}, "links": [{"rel": "self", "href": "https://dadosabertos.camara.leg.br/api/v2/deputados/141392"}]}