{"dados": {"id": 141491, "uri": "https://dadosabertos.camara.leg.br/api/v2/deputados/141491", "nomeCivil": "MANOEL FERREIRA", "ultimoStatus": {"id": 141491, "uri": "https://dadosabertos.camara.leg.br/api/v2/deputados/141491", "nome": "PASTOR MANOEL FERREIRA", "siglaPartido": "PR", "uriPartido": null, "siglaUf": "RJ", "idLegislatura": 53, "urlFoto": "https://www.camara.leg.br/internet/deputado/bandep/141491.jpg", "email": null, "data": "2011-01-31", "nomeEleitoral": "PASTOR MANOEL FERREIRA", "gabinete": {"nome": null, "predio": null, "sala": null, "andar": null, "telefone": null, "email": null}, "situacao": "Fim de Mandato", "condicaoEleitoral": "Titular", "descricaoStatus": null}, "cpf": "13962884815", "sexo": "M", "urlWebsite": null, "redeSocial": [], "dataNascimento": "1932-05-30", "dataFalecimento": null, "ufNascimento": "SP", "municipioNascimento": "Cafelândia", "escolaridade": "Superior"}, "links": [{"rel": "self", "href": "https://dadosabertos.camara.leg.br/api/v2/deputados/141491"}]}