{"dados": {"id": 141515, "uri": "https://dadosabertos.camara.leg.br/api/v2/deputados/141515", "nomeCivil": "OTAVIO SANTOS SILVA LEITE", "ultimoStatus": {"id": 141515, "uri": "https://dadosabertos.camara.leg.br/api/v2/deputados/141515", "nome": "Otavio Leite", "siglaPartido": "PSDB", "uriPartido": null, "siglaUf": "RJ", "idLegislatura": 56, "urlFoto": "https://www.camara.leg.br/internet/deputado/bandep/141515.jpg", "email": null, "data": "2022-04-01", "nomeEleitoral": "Otavio Leite", "gabinete": {"nome": null, "predio": null, "sala": null, "andar": null, "telefone": null, "email": null}, "situacao": "Suplência", "condicaoEleitoral": "Suplente", "descricaoStatus": null}, "cpf": "20163452504", "sexo": "M", "urlWebsite": null, "redeSocial": ["https://twitter.com/otavioleite", "https://www.facebook.com/OtavioLeiteRJ"], "dataNascimento": "1961-07-29", "dataFalecimento": null, "ufNascimento": "SE", "municipioNascimento": "Aracaju", "escolaridade": "Mestrado Incompleto"}, "links": [{"rel": "self", "href": "https://dadosabertos.camara.leg.br/api/v2/deputados/141515"}]}