{"dados": {"id": 156190, "uri": "https://dadosabertos.camara.leg.br/api/v2/deputados/156190", "nomeCivil": "MARCEL VAN HATTEM", "ultimoStatus": {"id": 156190, "uri": "https://dadosabertos.camara.leg.br/api/v2/deputados/156190", "nome": "Marcel van Hattem", "siglaPartido": "NOVO", "uriPartido": null, "siglaUf": "RS", "idLegislatura": 57, "urlFoto": "https://www.camara.leg.br/internet/deputado/bandep/156190.jpg", "email": null, "data": "2023-02-01", "nomeEleitoral": "Marcel van Hattem", "gabinete": {"nome": "958", "predio": "4", "sala": "958", "andar": "9", "telefone": "3215-5958", "email": "dep.marcelvanhattem@camara.leg.br"}, "situacao": "Exercício", "condicaoEleitoral": "Titular", "descricaoStatus": null}, "cpf": "00731302060", "sexo": "M", "urlWebsite": null, "redeSocial": ["https://twitter.com/MARCELVANHATTEM", "https://www.facebook.com/MARCELVH", "https://www.instagram.com/MARCELVANHATTEM", "https://youtube.com/channel/UCAGHY76tgzPiiXpJtM1sVCg"], "dataNascimento": "1985-11-08", "dataFalecimento": null, "ufNascimento": "RS", "municipioNascimento": "São Leopoldo", "escolaridade": "Mestrado"}, "links": [{"rel": "self", "href": "https://dadosabertos.camara.leg.br/api/v2/deputados/156190"}]}