{"dados": {"id": 1575, "uri": "https://dadosabertos.camara.leg.br/api/v2/deputados/1575", "nomeCivil": "Aristides de Souza Spínola", "ultimoStatus": {"id": 1575, "uri": "https://dadosabertos.camara.leg.br/api/v2/deputados/1575", "nome": "ARISTIDES ESPÍNOLA", "siglaPartido": null, "uriPartido": null, "siglaUf": "BA", "idLegislatura": 28, "urlFoto": "https://www.camara.leg.br/internet/deputado/bandep/1575.jpg", "email": null, "data": null, "nomeEleitoral": "ARISTIDES ESPÍNOLA", "gabinete": {"nome": null, "predio": null, "sala": null, "andar": null, "telefone": null, "email": null}, "situacao": "Vacância", "condicaoEleitoral": "Titular", "descricaoStatus": null}, "cpf": null, "sexo": "M", "urlWebsite": null, "redeSocial": [], "dataNascimento": "1850-08-29", "dataFalecimento": null, "ufNascimento": "BA", "municipioNascimento": null, "escolaridade": "Superior"}, "links": [{"rel": "self", "href": "https://dadosabertos.camara.leg.br/api/v2/deputados/1575"}]}