{"dados": {"id": 178827, "uri": "https://dadosabertos.camara.leg.br/api/v2/deputados/178827", "nomeCivil": "MAX FREITAS MAURO FILHO", "ultimoStatus": {"id": 178827, "uri": "https://dadosabertos.camara.leg.br/api/v2/deputados/178827", "nome": "MAX FILHO", "siglaPartido": "PSDB", "uriPartido": null, "siglaUf": "ES", "idLegislatura": 55, "urlFoto": "https://www.camara.leg.br/internet/deputado/bandep/178827.jpg", "email": null, "data": "2017-01-01", "nomeEleitoral": "MAX FILHO", "gabinete": {"nome": null, "predio": null, "sala": null, "andar": null, "telefone": null, "email": null}, "situacao": "Vacância", "condicaoEleitoral": "Titular", "descricaoStatus": "Prefeito de Vila Velha"}, "cpf": "98941917700", "sexo": "M", "urlWebsite": null, "redeSocial": ["https://https//www.facebook.com/max.maurofilho", "https://twitter.com/MaxMauroFilho"], "dataNascimento": "1968-06-24", "dataFalecimento": null, "ufNascimento": "ES", "municipioNascimento": "Vila Velha", "escolaridade": "Mestrado"}, "links": [{"rel": "self", "href": "https://dadosabertos.camara.leg.br/api/v2/deputados/178827"}]}