{"dados": {"id": 204378, "uri": "https://dadosabertos.camara.leg.br/api/v2/deputados/204378", "nomeCivil": "JOÃO CHRISÓSTOMO DE MOURA", "ultimoStatus": {"id": 204378, "uri": "https://dadosabertos.camara.leg.br/api/v2/deputados/204378", "nome": "Coronel Chrisóstomo", "siglaPartido": "PL", "uriPartido": null, "siglaUf": "RO", "idLegislatura": 57, "urlFoto": "https://www.camara.leg.br/internet/deputado/bandep/204378.jpg", "email": null, "data": "2023-02-01", "nomeEleitoral": "Coronel Chrisóstomo", "gabinete": {"nome": "672", "predio": "3", "sala": "672", "andar": null, "telefone": "3215-5672", "email": "dep.coronelchrisostomo@camara.leg.br"}, "situacao": "Exercício", "condicaoEleitoral": "Titular", "descricaoStatus": null}, "cpf": "70335591787", "sexo": "M", "urlWebsite": null, "redeSocial": [], "dataNascimento": "1959-06-23", "dataFalecimento": null, "ufNascimento": "AM", "municipioNascimento": "Tefé", "escolaridade": "Superior"}, "links": [{"rel": "self", "href": "https://dadosabertos.camara.leg.br/api/v2/deputados/204378"}]}