{"dados": {"id": 220572, "uri": "https://dadosabertos.camara.leg.br/api/v2/deputados/220572", "nomeCivil": "MARUSSA CASSIA FAVARO BOLDRIN VAZ", "ultimoStatus": {"id": 220572, "uri": "https://dadosabertos.camara.leg.br/api/v2/deputados/220572", "nome": "Marussa Boldrin", "siglaPartido": "MDB", "uriPartido": null, "siglaUf": "GO", "idLegislatura": 57, "urlFoto": "https://www.camara.leg.br/internet/deputado/bandep/220572.jpg", "email": null, "data": "2023-02-01", "nomeEleitoral": "Marussa Boldrin", "gabinete": {"nome": "574", "predio": "3", "sala": "574", "andar": null, "telefone": "3215-5574", "email": "dep.marussaboldrin@camara.leg.br"}, "situacao": "Exercício", "condicaoEleitoral": "Titular", "descricaoStatus": null}, "cpf": "02710089114", "sexo": "F", "urlWebsite": null, "redeSocial": ["https://twitter.com/marussago", "https://www.facebook.com/marussaboldrin.go", "https://www.instagram.com/marussa.boldrin"], "dataNascimento": "1990-06-25", "dataFalecimento": null, "ufNascimento": "GO", "municipioNascimento": "Rio Verde", "escolaridade": "Superior"}, "links": [{"rel": "self", "href": "https://dadosabertos.camara.leg.br/api/v2/deputados/220572"}]}