{"dados": {"id": 222429, "uri": "https://dadosabertos.camara.leg.br/api/v2/deputados/222429", "nomeCivil": "LUIS CARLOS GOMES DA SILVA", "ultimoStatus": {"id": 222429, "uri": "https://dadosabertos.camara.leg.br/api/v2/deputados/222429", "nome": "Luis Carlos Gomes", "siglaPartido": "REPUBLICANOS", "uriPartido": null, "siglaUf": "RJ", "idLegislatura": 57, "urlFoto": "https://www.camara.leg.br/internet/deputado/bandep/222429.jpg", "email": null, "data": "2024-12-06", "nomeEleitoral": "Luis Carlos Gomes", "gabinete": {"nome": "438", "predio": "4", "sala": "438", "andar": "4", "telefone": "3215-5438", "email": "dep.luiscarlosgomes@camara.leg.br"}, "situacao": "Exercício", "condicaoEleitoral": "Suplente", "descricaoStatus": null}, "cpf": "88394468772", "sexo": "M", "urlWebsite": null, "redeSocial": [], "dataNascimento": "1966-05-05", "dataFalecimento": null, "ufNascimento": "RJ", "municipioNascimento": "Rio de Janeiro", "escolaridade": "Superior"}, "links": [{"rel": "self", "href": "https://dadosabertos.camara.leg.br/api/v2/deputados/222429"}]}