{"dados": {"id": 2658, "uri": "https://dadosabertos.camara.leg.br/api/v2/deputados/2658", "nomeCivil": "Paulo Pinheiro da Silva", "ultimoStatus": {"id": 2658, "uri": "https://dadosabertos.camara.leg.br/api/v2/deputados/2658", "nome": "PAULO PINHEIRO", "siglaPartido": null, "uriPartido": null, "siglaUf": "MG", "idLegislatura": 35, "urlFoto": "https://www.camara.leg.br/internet/deputado/bandep/2658.jpg", "email": null, "data": null, "nomeEleitoral": "PAULO PINHEIRO", "gabinete": {"nome": null, "predio": null, "sala": null, "andar": null, "telefone": null, "email": null}, "situacao": null, "condicaoEleitoral": null, "descricaoStatus": null}, "cpf": null, "sexo": "M", "urlWebsite": null, "redeSocial": [], "dataNascimento": "1890-12-23", "dataFalecimento": null, "ufNascimento": "MG", "municipioNascimento": "Ouro Preto", "escolaridade": null}, "links": [{"rel": "self", "href": "https://dadosabertos.camara.leg.br/api/v2/deputados/2658"}]}