{"dados": {"id": 3140, "uri": "https://dadosabertos.camara.leg.br/api/v2/deputados/3140", "nomeCivil": "Simão da Cunha Pereira", "ultimoStatus": {"id": 3140, "uri": "https://dadosabertos.camara.leg.br/api/v2/deputados/3140", "nome": "SIMÃO DA CUNHA PEREIRA", "siglaPartido": null, "uriPartido": null, "siglaUf": "MG", "idLegislatura": 23, "urlFoto": "https://www.camara.leg.br/internet/deputado/bandep/3140.jpg", "email": null, "data": null, "nomeEleitoral": "SIMÃO DA CUNHA PEREIRA", "gabinete": {"nome": null, "predio": null, "sala": null, "andar": null, "telefone": null, "email": null}, "situacao": "Vacância", "condicaoEleitoral": null, "descricaoStatus": null}, "cpf": null, "sexo": "M", "urlWebsite": null, "redeSocial": [], "dataNascimento": "1859-05-24", "dataFalecimento": null, "ufNascimento": "MG", "municipioNascimento": "Serro", "escolaridade": "Superior"}, "links": [{"rel": "self", "href": "https://dadosabertos.camara.leg.br/api/v2/deputados/3140"}]}