{"dados": {"id": 4205, "uri": "https://dadosabertos.camara.leg.br/api/v2/deputados/4205", "nomeCivil": "João Pandiá Calógeras", "ultimoStatus": {"id": 4205, "uri": "https://dadosabertos.camara.leg.br/api/v2/deputados/4205", "nome": "PANDIÁ CALÓGERAS", "siglaPartido": "PP**", "uriPartido": null, "siglaUf": "MG", "idLegislatura": 36, "urlFoto": "https://www.camara.leg.br/internet/deputado/bandep/4205.jpg", "email": null, "data": null, "nomeEleitoral": "PANDIÁ CALÓGERAS", "gabinete": {"nome": null, "predio": null, "sala": null, "andar": null, "telefone": null, "email": null}, "situacao": "Vacância", "condicaoEleitoral": "Titular", "descricaoStatus": null}, "cpf": null, "sexo": "M", "urlWebsite": null, "redeSocial": [], "dataNascimento": "1870-06-19", "dataFalecimento": null, "ufNascimento": "RJ", "municipioNascimento": "Rio de Janeiro", "escolaridade": null}, "links": [{"rel": "self", "href": "https://dadosabertos.camara.leg.br/api/v2/deputados/4205"}]}