{"dados": {"id": 568, "uri": "https://dadosabertos.camara.leg.br/api/v2/deputados/568", "nomeCivil": "Francisco Domingues da Silva", "ultimoStatus": {"id": 568, "uri": "https://dadosabertos.camara.leg.br/api/v2/deputados/568", "nome": "DOMINGUES DA SILVA", "siglaPartido": null, "uriPartido": null, "siglaUf": "CE", "idLegislatura": 16, "urlFoto": "https://www.camara.leg.br/internet/deputado/bandep/568.jpg", "email": null, "data": null, "nomeEleitoral": "DOMINGUES DA SILVA", "gabinete": {"nome": null, "predio": null, "sala": null, "andar": null, "telefone": null, "email": null}, "situacao": null, "condicaoEleitoral": null, "descricaoStatus": null}, "cpf": null, "sexo": "M", "urlWebsite": null, "redeSocial": [], "dataNascimento": "1812-09-15", "dataFalecimento": null, "ufNascimento": null, "municipioNascimento": null, "escolaridade": null}, "links": [{"rel": "self", "href": "https://dadosabertos.camara.leg.br/api/v2/deputados/568"}]}