{"dados": {"id": 73770, "uri": "https://dadosabertos.camara.leg.br/api/v2/deputados/73770", "nomeCivil": "Luiz Fernando Ribas Carli", "ultimoStatus": {"id": 73770, "uri": "https://dadosabertos.camara.leg.br/api/v2/deputados/73770", "nome": "FERNANDO RIBAS CARLI", "siglaPartido": "PPB", "uriPartido": null, "siglaUf": "PR", "idLegislatura": 50, "urlFoto": "https://www.camara.leg.br/internet/deputado/bandep/73770.jpg", "email": null, "data": null, "nomeEleitoral": "FERNANDO RIBAS CARLI", "gabinete": {"nome": null, "predio": null, "sala": null, "andar": null, "telefone": null, "email": null}, "situacao": "Afastado", "condicaoEleitoral": "Titular", "descricaoStatus": null}, "cpf": "05643813904", "sexo": "M", "urlWebsite": null, "redeSocial": [], "dataNascimento": "1949-10-09", "dataFalecimento": null, "ufNascimento": "PR", "municipioNascimento": "Guarapuava", "escolaridade": "Superior"}, "links": [{"rel": "self", "href": "https://dadosabertos.camara.leg.br/api/v2/deputados/73770"}]}