{"dados": {"id": 73969, "uri": "https://dadosabertos.camara.leg.br/api/v2/deputados/73969", "nomeCivil": "Makoto Iguchi", "ultimoStatus": {"id": 73969, "uri": "https://dadosabertos.camara.leg.br/api/v2/deputados/73969", "nome": "MAKOTO IGUCHI", "siglaPartido": "PSDB", "uriPartido": null, "siglaUf": "SP", "idLegislatura": 49, "urlFoto": "https://www.camara.leg.br/internet/deputado/bandep/73969.jpg", "email": null, "data": null, "nomeEleitoral": "MAKOTO IGUCHI", "gabinete": {"nome": null, "predio": null, "sala": null, "andar": null, "telefone": null, "email": null}, "situacao": null, "condicaoEleitoral": "Titular", "descricaoStatus": null}, "cpf": "19579187800", "sexo": "M", "urlWebsite": null, "redeSocial": [], "dataNascimento": "1937-05-10", "dataFalecimento": null, "ufNascimento": "SP", "municipioNascimento": "São Paulo", "escolaridade": "Superior"}, "links": [{"rel": "self", "href": "https://dadosabertos.camara.leg.br/api/v2/deputados/73969"}]}