{"dados": {"id": 74270, "uri": "https://dadosabertos.camara.leg.br/api/v2/deputados/74270", "nomeCivil": "GILBERTO NASCIMENTO SILVA", "ultimoStatus": {"id": 74270, "uri": "https://dadosabertos.camara.leg.br/api/v2/deputados/74270", "nome": "Gilberto Nascimento", "siglaPartido": "PSD", "uriPartido": null, "siglaUf": "SP", "idLegislatura": 57, "urlFoto": "https://www.camara.leg.br/internet/deputado/bandep/74270.jpg", "email": null, "data": "2023-02-01", "nomeEleitoral": "Gilberto Nascimento", "gabinete": {"nome": "836", "predio": "4", "sala": "836", "andar": "8", "telefone": "3215-5836", "email": "dep.gilbertonascimento@camara.leg.br"}, "situacao": "Exercício", "condicaoEleitoral": "Titular", "descricaoStatus": null}, "cpf": "64817407891", "sexo": "M", "urlWebsite": null, "redeSocial": [], "dataNascimento": "1956-07-09", "dataFalecimento": null, "ufNascimento": "SP", "municipioNascimento": "São Paulo", "escolaridade": "Superior"}, "links": [{"rel": "self", "href": "https://dadosabertos.camara.leg.br/api/v2/deputados/74270"}]}