{"dados": {"id": 74469, "uri": "https://dadosabertos.camara.leg.br/api/v2/deputados/74469", "nomeCivil": "INALDO ROCHA LEITÃO", "ultimoStatus": {"id": 74469, "uri": "https://dadosabertos.camara.leg.br/api/v2/deputados/74469", "nome": "INALDO LEITÃO", "siglaPartido": "PR", "uriPartido": null, "siglaUf": "PB", "idLegislatura": 52, "urlFoto": "https://www.camara.leg.br/internet/deputado/bandep/74469.jpg", "email": null, "data": "2006-09-08", "nomeEleitoral": "INALDO LEITÃO", "gabinete": {"nome": null, "predio": null, "sala": null, "andar": null, "telefone": null, "email": null}, "situacao": "Suplência", "condicaoEleitoral": "Suplente", "descricaoStatus": null}, "cpf": "07466161472", "sexo": "M", "urlWebsite": null, "redeSocial": [], "dataNascimento": "1951-11-04", "dataFalecimento": null, "ufNascimento": "PB", "municipioNascimento": "Sousa", "escolaridade": "Superior"}, "links": [{"rel": "self", "href": "https://dadosabertos.camara.leg.br/api/v2/deputados/74469"}]}