{"dados": {"id": 74779, "uri": "https://dadosabertos.camara.leg.br/api/v2/deputados/74779", "nomeCivil": "HÉLIO DE OLIVEIRA SANTOS", "ultimoStatus": {"id": 74779, "uri": "https://dadosabertos.camara.leg.br/api/v2/deputados/74779", "nome": "DR. HÉLIO", "siglaPartido": "PDT", "uriPartido": null, "siglaUf": "SP", "idLegislatura": 52, "urlFoto": "https://www.camara.leg.br/internet/deputado/bandep/74779.jpg", "email": null, "data": "2005-01-01", "nomeEleitoral": "DR. HÉLIO", "gabinete": {"nome": null, "predio": null, "sala": null, "andar": null, "telefone": null, "email": null}, "situacao": "Vacância", "condicaoEleitoral": "Titular", "descricaoStatus": "Prefeito de Campinas (SP) (Publicado no DCD nº 1, de 01/01/05.)"}, "cpf": "72111470830", "sexo": "M", "urlWebsite": null, "redeSocial": [], "dataNascimento": "1950-09-06", "dataFalecimento": null, "ufNascimento": "MS", "municipioNascimento": "Corumbá", "escolaridade": "Superior"}, "links": [{"rel": "self", "href": "https://dadosabertos.camara.leg.br/api/v2/deputados/74779"}]}