{"dados": {"id": 74792, "uri": "https://dadosabertos.camara.leg.br/api/v2/deputados/74792", "nomeCivil": "LUIZ CARLOS DA SILVA", "ultimoStatus": {"id": 74792, "uri": "https://dadosabertos.camara.leg.br/api/v2/deputados/74792", "nome": "PROFESSOR LUIZINHO", "siglaPartido": "PT", "uriPartido": null, "siglaUf": "SP", "idLegislatura": 52, "urlFoto": "https://www.camara.leg.br/internet/deputado/bandep/74792.jpg", "email": null, "data": "2007-01-31", "nomeEleitoral": "PROFESSOR LUIZINHO", "gabinete": {"nome": null, "predio": null, "sala": null, "andar": null, "telefone": null, "email": null}, "situacao": "Fim de Mandato", "condicaoEleitoral": "Titular", "descricaoStatus": null}, "cpf": "75918862820", "sexo": "M", "urlWebsite": null, "redeSocial": [], "dataNascimento": "1955-04-18", "dataFalecimento": null, "ufNascimento": "SP", "municipioNascimento": "Cândido Mota", "escolaridade": "Superior"}, "links": [{"rel": "self", "href": "https://dadosabertos.camara.leg.br/api/v2/deputados/74792"}]}