{"dados": {"id": 771, "uri": "https://dadosabertos.camara.leg.br/api/v2/deputados/771", "nomeCivil": "Tobias Rabello Leite", "ultimoStatus": {"id": 771, "uri": "https://dadosabertos.camara.leg.br/api/v2/deputados/771", "nome": "TOBIAS LEITE", "siglaPartido": null, "uriPartido": null, "siglaUf": "SE", "idLegislatura": 10, "urlFoto": "https://www.camara.leg.br/internet/deputado/bandep/771.jpg", "email": null, "data": null, "nomeEleitoral": "TOBIAS LEITE", "gabinete": {"nome": null, "predio": null, "sala": null, "andar": null, "telefone": null, "email": null}, "situacao": "Vacância", "condicaoEleitoral": "Suplente", "descricaoStatus": null}, "cpf": null, "sexo": "M", "urlWebsite": null, "redeSocial": [], "dataNascimento": "1827-04-06", "dataFalecimento": null, "ufNascimento": "SE", "municipioNascimento": null, "escolaridade": "Superior"}, "links": [{"rel": "self", "href": "https://dadosabertos.camara.leg.br/api/v2/deputados/771"}]}